LICENSE.txt
LICENSE_Python.txt
MANIFEST.in
README.rst
_line_profiler.c
_line_profiler.pyx
kernprof.py
line_profiler.py
line_profiler_py35.py
python25.pxd
setup.py
timers.c
timers.h
unset_trace.c
unset_trace.h
lp37.egg-info/PKG-INFO
lp37.egg-info/SOURCES.txt
lp37.egg-info/dependency_links.txt
lp37.egg-info/entry_points.txt
lp37.egg-info/top_level.txt
tests/_test_kernprof_py35.py
tests/test_kernprof.py
tests/test_line_profiler.py