Metadata-Version: 1.1
Name: lp37
Version: 2.1.1
Summary: Line-by-line profiler. Fork with Python 3.7 compatibility.
Home-page: https://github.com/rkern/line_profiler
Author: Robert Kern
Author-email: robert.kern@enthought.com
License: BSD
Download-URL: https://github.com/rkern/line_profiler/tarball/2.1
Keywords: timing,timer,profiling,profiler,line_profiler
Platform: UNKNOWN
Classifier: Development Status :: 5 - Production/Stable
Classifier: Intended Audience :: Developers
Classifier: License :: OSI Approved :: BSD License
Classifier: Operating System :: OS Independent
Classifier: Programming Language :: C
Classifier: Programming Language :: Python
Classifier: Programming Language :: Python :: 2
Classifier: Programming Language :: Python :: 2.7
Classifier: Programming Language :: Python :: 3
Classifier: Programming Language :: Python :: 3.2
Classifier: Programming Language :: Python :: 3.3
Classifier: Programming Language :: Python :: 3.4
Classifier: Programming Language :: Python :: 3.5
Classifier: Programming Language :: Python :: 3.6
Classifier: Programming Language :: Python :: 3.7
Classifier: Programming Language :: Python :: Implementation :: CPython
Classifier: Topic :: Software Development
